billogram/__init__.py
billogram/__version__.py
billogram/py.typed
billogram-0.0.0.dist-info/LICENSE
billogram-0.0.0.dist-info/WHEEL
billogram-0.0.0.dist-info/METADATA
billogram-0.0.0.dist-info/RECORD
